{
  "sessionId": "session_20251213T222346_loxhsns",
  "gameId": "all_92_games/cookie-clicker",
  "userId": "652d8a4cd08c6435db58fd9b",
  "startTime": "2025-12-13T22:23:46.859Z",
  "endTime": "2025-12-13T22:26:30.504Z",
  "duration": 164,
  "fps": 30,
  "videoWidth": 1200,
  "videoHeight": 800,
  "completed": true,
  "deviceInfo": {
    "userAgent": "Mozilla/5.0 (Macintosh; Intel Mac OS X 10_15_7) AppleWebKit/537.36 (KHTML, like Gecko) Chrome/143.0.0.0 Safari/537.36",
    "screenWidth": 1440,
    "screenHeight": 900,
    "screenDepth": 30,
    "screenPixelDepth": 30,
    "devicePixelRatio": 2,
    "timezone": "America/Chicago",
    "language": "en-US",
    "hardwareConcurrency": 8,
    "deviceMemory": 8,
    "maxTouchPoints": 0,
    "platform": "MacIntel",
    "vendor": "Google Inc.",
    "ip": null
  }
}